{
    "version": "4.5.4",
    "flags": {},
    "shapes": [
        {
            "label": "zone",
            "points": [
                [
                    129.25806451612902,
                    637.8709677419355
                ],
                [
                    47.806451612903224,
                    191.09677419354838
                ],
                [
                    522.0,
                    147.5483870967742
                ],
                [
                    1158.2903225806451,
                    457.2258064516129
                ]
            ],
            "group_id": null,
            "shape_type": "polygon",
            "flags": {}
        },
        {
            "label": "direction01",
            "points": [
                [
                    155.8709677419355,
                    166.09677419354838
                ],
                [164, 175],
                [176, 185],
                [183, 198],
                [192, 203],
                [199, 212],
                [209, 222],
                [220, 237],
                [232, 248],
                [244, 256],
                [257, 270],
                [269, 285],
                [282, 298],
                [296, 313],
                [312, 329],
                [330, 342],
                [345, 365],
                [363, 386],
                [379, 399],
                [396, 418],
                [409, 429],
                [426, 446],
                [443, 462],
                [462, 479],
                [476, 495],
                [491, 512],
                [508, 529],
                [526, 549],
                [540, 562],
                [
                    596.1935483870968,
                    621.741935483871
                ]
            ],
            "group_id": null,
            "shape_type": "line",
            "flags": {}
        },
        {
            "label": "direction02",
            "points": [
                [207, 160],
                [217, 168],
                [228, 170],
                [242, 177],
                [258, 182],
                [273, 188],
                [296, 193],
                [311, 196],
                [346, 201],
                [371, 201],
                [398, 200],
                [428, 202],
                [453, 202],
                [481, 205],
                [508, 204],
                [552, 205],
                [579, 207],
                [610, 205],
                [641, 205],
                [667, 206],
                [685, 206],
                [707, 208],
                [724, 210]
            ],
            "group_id": null,
            "shape_type": "line",
            "flags": {}
        },
        {
            "label": "direction03",
            "points": [
                [963, 310],
                [953, 315],
                [940, 321],
                [925, 329],
                [909, 339],
                [887, 352],
                [875, 361],
                [866, 374],
                [860, 386],
                [860, 399],
                [865, 412],
                [872, 427],
                [883, 437],
                [900, 453],
                [916, 473],
                [933, 493],
                [952, 505],
                [971, 524],
                [990, 533],
                [1015, 550]

            ],
            "group_id": null,
            "shape_type": "line",
            "flags": {}
        }
    ],
    "imagePath": "cam_16.png",
    "imageData": null,
    "imageHeight": 720,
    "imageWidth": 1280
}
